tk_db_tool/__init__.py
tk_db_tool/curd.py
tk_db_tool/datebase.py
tk_db_tool/message.py
tk_db_tool/models.py
tk_db_tool/utlis.py
tk_db_tool-0.1.2.dist-info/licenses/LICENSE
tk_db_tool-0.1.2.dist-info/METADATA
tk_db_tool-0.1.2.dist-info/WHEEL
tk_db_tool-0.1.2.dist-info/top_level.txt
tk_db_tool-0.1.2.dist-info/RECORD
