Metadata-Version: 2.4
Name: tk-db-tool
Version: 0.1.2
Summary: Add your description here
Requires-Python: >=3.11
License-File: LICENSE
Requires-Dist: pydantic>=2.11.4
Requires-Dist: pymysql>=1.1.1
Requires-Dist: python-dotenv>=1.1.0
Requires-Dist: sqlalchemy>=2.0.40
Dynamic: license-file
